blockbuilder/__init__.py
blockbuilder/block.py
blockbuilder/core_plotter.py
blockbuilder/element.py
blockbuilder/grid.py
blockbuilder/help.py
blockbuilder/interactive_plotter.py
blockbuilder/intersection.py
blockbuilder/main_plotter.py
blockbuilder/minimal_plotter.py
blockbuilder/params.py
blockbuilder/plane.py
blockbuilder/selector.py
blockbuilder/setting.py
blockbuilder/utils.py
blockbuilder/app/__init__.py
blockbuilder/app/start.py
blockbuilder/icons/__init__.py
blockbuilder/icons/resources.py
blockbuilder-0.6.0.data/scripts/blockbuilder
blockbuilder-0.6.0.dist-info/LICENSE
blockbuilder-0.6.0.dist-info/METADATA
blockbuilder-0.6.0.dist-info/WHEEL
blockbuilder-0.6.0.dist-info/top_level.txt
blockbuilder-0.6.0.dist-info/RECORD
