Metadata-Version: 2.1
Name: blockbuilder
Version: 0.6.0
Summary: Block building application
Home-page: http://github.com/GuillaumeFavelier/blockbuilder
Author: Guillaume Favelier
Author-email: guillaume.favelier@gmail.com
License: BSD (3-clause)
Download-URL: http://github.com/GuillaumeFavelier/blockbuilder
Platform: Windows
Platform: Linux
Platform: MacOS
Classifier: Operating System :: Microsoft :: Windows
Classifier: Operating System :: POSIX :: Linux
Classifier: Operating System :: MacOS :: MacOS X
Classifier: License :: OSI Approved :: BSD License
Classifier: Programming Language :: Python :: 3
Classifier: Development Status :: 2 - Pre-Alpha
Classifier: Intended Audience :: End Users/Desktop
Classifier: Intended Audience :: Developers
Classifier: Topic :: Artistic Software
Classifier: Topic :: Software Development
Requires-Python: >=3.7
Requires-Dist: numpy (>=1.18.5)
Requires-Dist: vtk (>=8.1.2)
Requires-Dist: qtpy (>=1.9.0)
